[
  {
    "date": "2025-05-13",
    "card": "3530",
    "status": "SUCCESS",
    "txn_count": 8,
    "statement_id": 295
  },
  {
    "date": "2025-06-13",
    "card": "3530",
    "status": "SUCCESS",
    "txn_count": 7,
    "statement_id": 296
  },
  {
    "date": "2025-07-13",
    "card": "3530",
    "status": "SUCCESS",
    "txn_count": 11,
    "statement_id": 297
  },
  {
    "date": "2025-08-13",
    "card": "3530",
    "status": "SUCCESS",
    "txn_count": 26,
    "statement_id": 298
  },
  {
    "date": "2025-09-13",
    "card": "3530",
    "status": "SUCCESS",
    "txn_count": 18,
    "statement_id": 299
  },
  {
    "date": "2025-10-13",
    "card": "8387",
    "status": "SUCCESS",
    "txn_count": 8,
    "statement_id": 300
  }
]